{
  "$schema": "https://biomejs.dev/schemas/2.3.8/schema.json",
  "extends": "//",
  "linter": {
    "rules": {
      "suspicious": {
        "noConsole": {
          "level": "error",
          "options": {
            "allow": ["error", "time", "timeEnd"]
          },
          "fix": "none"
        }
      }
    }
  },
  "formatter": {
    "lineWidth": 80,
    "enabled": true,
    "indentWidth": 2,
    "indentStyle": "space",
    "formatWithErrors": true
  },
  "files": {
    "maxSize": 10485760,
    "ignoreUnknown": true,
    "includes": [
      "src/**/*.ts",
      "src/**/*.json",
      "scalingo/cron.json",
      "biome.json",
      "tsconfig.json",
      "tsconfig.prod.json",
      "babel.config.js",
      "package.json"
    ]
  }
}
